<?xml version="1.0" encoding="GBK"?>
<resource>
  <model name="单表数据库操作" page="single-table.jsp" wizard-class="cn.gwssi.console.txn.wizard.TableModuleWizard" demo-image="single-table.gif"/>
  <struts name="ad_mon_caree.xml" app-path="/dw/aic/bj/ad/syfr/" app-name="ad_mon_caree" description="事业法人" template="single-table.xml"/>
  <table name="ad_mon_caree.xml" app-name="ad_mon_caree" app-desc="事业法人" delete-action="delete" description="事业法人" class-name="com.gwssi.dw.aic.bj.ad.txn.TxnAdMonCaree" template="single-table.java" dao-class-template="single-table.java">
	  <jsp page-name="query-ad_mon_caree.jsp" txn-code="60188001" description="查询事业法人列表" template="single/single-table-query.jsp">
	    <button type="button" name="增加事业法人" path="insert-ad_mon_caree.jsp" description="增加事业法人" func-name="addRecord"/>
	    <button type="button" name="修改事业法人" path="/txn60188004.do" description="修改事业法人" func-name="updateRecord"/>
	    <button type="button" name="删除事业法人" path="/txn60188005.do" description="删除事业法人" func-name="deleteRecord"/>
	    <button type="button" name="查 询" path="/txn60188001.do" description="查询事业法人信息" func-name="submit"/>
	  </jsp>
	  <jsp page-name="insert-ad_mon_caree.jsp" txn-code="60188003" description="增加事业法人信息" template="single/single-table-insert.jsp">
	    <button type="button" name="保 存" path="/txn60188003.do" description="保存事业法人信息" func-name="saveRecord"/>
	    <button type="button" name="保存并继续" path="/txn60188003.do" description="保存事业法人信息并继续" func-name="saveAndContinue"/>
	    <button type="button" name="保存并关闭" path="/txn60188001.do" description="保存事业法人信息并返回" func-name="saveAndExit"/>
	    <button type="button" name="返 回" path="/txn60188001.do" description="返回到事业法人明细窗口" func-name="goBack"/>
	  </jsp>
	  <jsp page-name="update-ad_mon_caree.jsp" txn-code="60188002" description="修改事业法人信息" template="single/single-table-update.jsp">
	    <button type="button" name="保 存" path="/txn60188001.do" description="修改事业法人信息" func-name="saveAndExit"/>
	    <button type="button" name="返 回" path="/txn60188001.do" description="返回到明细窗口" func-name="goBack"/>
	  </jsp>

	  <txn input="query-ad_mon_caree.jsp" txn-code="60188001" description="查询事业法人列表">
	    <forward error-code="success" path="query-ad_mon_caree.jsp" description="成功时返回列表"/>
	    <forward error-code="failure" path="query-ad_mon_caree.jsp" description="错误时返回错误信息"/>
	  </txn>
	  <txn input="update-ad_mon_caree.jsp" txn-code="60188002" description="修改事业法人信息">
	    <forward error-code="success" path="update-ad_mon_caree.jsp" description="成功时返回页面"/>
	    <forward error-code="failure" path="update-ad_mon_caree.jsp" description="错误时返回页面"/>
	  </txn>
	  <txn input="insert-ad_mon_caree.jsp" txn-code="60188003" description="增加事业法人信息">
	    <forward error-code="success" path="insert-ad_mon_caree.jsp" description="成功时返回页面"/>
	    <forward error-code="failure" path="insert-ad_mon_caree.jsp" description="错误时返回页面"/>
	  </txn>
	  <txn input="query-ad_mon_caree.jsp" txn-code="60188004" description="查询事业法人用于修改">
	    <forward error-code="success" path="update-ad_mon_caree.jsp" description="成功时返回记录"/>
	    <forward error-code="failure" path="update-ad_mon_caree.jsp" description="错误时返回页面"/>
	  </txn>
	  <txn input="query-ad_mon_caree.jsp" txn-code="60188005" description="删除事业法人信息">
	    <forward error-code="success" path="/script/deletesuccess.jsp" description="成功时返回提示页面"/>
	    <forward error-code="failure" path="/script/deletefailure.jsp" description="错误时返回提示页面"/>
	  </txn>
	  <vo clazz-name="com.gwssi.dw.aic.bj.ad.vo.AdMonCareeContext" description="应用对应的数据上下文对象" template="single-table-context.java"/>
	  <vo clazz-name="com.gwssi.dw.aic.bj.ad.vo.VoAdMonCaree" description="数据表字段对应的VO对象" template="single-table-vo.java"/>
	  <vo clazz-name="com.gwssi.dw.aic.bj.ad.vo.VoAdMonCareeSelectKey" description="查询条件对应的VO对象" template="single-table-vo-select-key.java"/>
	  <vo clazz-name="com.gwssi.dw.aic.bj.ad.vo.VoAdMonCareePrimaryKey" description="数据库主键对应的VO对象" template="single-table-vo-primary-key.java"/>
  </table>
</resource>
